igraph/__init__.pyi
igraph/py.typed
ndspy/__init__.pyi
ndspy/code.pyi
ndspy/fnt.pyi
ndspy/py.typed
ndspy/rom.pyi
skytemple_3rdparty_typestubs-1.1.1.dist-info/LICENSE
skytemple_3rdparty_typestubs-1.1.1.dist-info/METADATA
skytemple_3rdparty_typestubs-1.1.1.dist-info/WHEEL
skytemple_3rdparty_typestubs-1.1.1.dist-info/top_level.txt
skytemple_3rdparty_typestubs-1.1.1.dist-info/RECORD
